recorder/__init__.py
recorder/__main__.py
recorder/config.py
recorder/device/__init__.py
recorder/device/device.py
recorder/device/microphone.py
recorder/device/realsense.py
recorder/io.py
recorder/listener/__init__.py
recorder/listener/listener.py
recorder/listener/localhost.py
recorder/recorder.py
python_recorder-0.0.4.dist-info/entry_points.txt
python_recorder-0.0.4.dist-info/WHEEL
python_recorder-0.0.4.dist-info/METADATA
python_recorder-0.0.4.dist-info/RECORD
