Metadata-Version: 2.1
Name: python-recorder
Version: 0.0.4
Summary: Device independent framework for synchronized recording, designed for researchers collecting multimodal datasets.
Home-page: https://github.com/AcousticOdometry/python-recorder
License: MIT
Author: Andreu Gimenez
Author-email: esdandreu@gmail.com
Requires-Python: >=3.8,<4.0
Classifier: License :: OSI Approved :: MIT License
Classifier: Programming Language :: Python :: 3
Classifier: Programming Language :: Python :: 3.8
Classifier: Programming Language :: Python :: 3.9
Classifier: Programming Language :: Python :: 3.10
Provides-Extra: all
Provides-Extra: realsense
Requires-Dist: Flask (>=2.1.1,<3.0.0)
Requires-Dist: PyInquirer (>=1.0.3,<2.0.0)
Requires-Dist: PyYAML (>=5.1,<6.0)
Requires-Dist: numpy (>=1.22.2,<2.0.0)
Requires-Dist: pyrealsense2 (>=2.50.0,<3.0.0); extra == "realsense" or extra == "all"
Requires-Dist: sounddevice (>=0.4.4,<0.5.0)
Requires-Dist: typer[all] (>=0.4.0,<0.5.0)
Project-URL: Repository, https://github.com/AcousticOdometry/python-recorder
